PyGSODTrend/__init__.py
PyGSODTrend/__main__.py
PyGSODTrend/data_cleaning.py
PyGSODTrend/trend_analysis.py
PyGSODTrend/visualization.py
pygsodtrend-0.1.0.dist-info/METADATA
pygsodtrend-0.1.0.dist-info/WHEEL
pygsodtrend-0.1.0.dist-info/entry_points.txt
pygsodtrend-0.1.0.dist-info/top_level.txt
pygsodtrend-0.1.0.dist-info/RECORD
