Metadata-Version: 2.4
Name: PyGSODTrend
Version: 0.1.0
Summary: Analyze and map climate trends from GSOD data using the Mann-Kendall test.
Author-email: Adithya Sridhar <adithya.sridh@gmail.com>
License-Expression: MIT
Project-URL: Repository, https://github.com/adsrx222/PyGSODTrend
Requires-Python: >=3.8
Requires-Dist: Cartopy==0.25.0
Requires-Dist: certifi==2025.8.3
Requires-Dist: contourpy==1.3.3
Requires-Dist: cycler==0.12.1
Requires-Dist: fonttools==4.60.1
Requires-Dist: kiwisolver==1.4.9
Requires-Dist: matplotlib==3.10.6
Requires-Dist: numpy==2.3.3
Requires-Dist: packaging==25.0
Requires-Dist: pandas==2.3.3
Requires-Dist: pillow==11.3.0
Requires-Dist: pymannkendall==1.4.3
Requires-Dist: pyparsing==3.2.5
Requires-Dist: pyproj==3.7.2
Requires-Dist: pyshp==2.3.1
Requires-Dist: python-dateutil==2.9.0.post0
Requires-Dist: pytz==2025.2
Requires-Dist: scipy==1.16.2
Requires-Dist: shapely==2.1.2
Requires-Dist: six==1.17.0
Requires-Dist: tzdata==2025.2
Requires-Dist: rich>=14.0
